Metadata-Version: 2.4
Name: adafruit-circuitpython-floppy
Version: 3.0.4
Summary: Access floppy drives from CircuitPython
Author-email: Adafruit Industries <circuitpython@adafruit.com>
License: MIT
Project-URL: Homepage, https://github.com/adafruit/Adafruit_CircuitPython_Floppy
Keywords: adafruit,floppy,drive,storage,hardware,micropythoncircuitpython
Classifier: Intended Audience :: Developers
Classifier: Topic :: Software Development :: Libraries
Classifier: Topic :: Software Development :: Embedded Systems
Classifier: Topic :: System :: Hardware
Classifier: License :: OSI Approved :: MIT License
Classifier: Programming Language :: Python :: 3
License-File: LICENSE
Requires-Dist: Adafruit-Blinka
Requires-Dist: adafruit-circuitpython-ticks
Provides-Extra: optional
Dynamic: license-file
